dbnd_docker/__init__.py
dbnd_docker/_plugin.py
dbnd_docker/container_engine_config.py
dbnd_docker/docker_ctrl.py
dbnd_docker/submit_ctrl.py
dbnd_docker/docker/__init__.py
dbnd_docker/docker/docker_build.py
dbnd_docker/docker/docker_engine_config.py
dbnd_docker/docker/docker_task.py
dbnd_docker/docker/docker_task_run_ctrl.py
dbnd_docker/kubernetes/__init__.py
dbnd_docker/kubernetes/dns1123_clean_names.py
dbnd_docker/kubernetes/kube_dbnd_client.py
dbnd_docker/kubernetes/kube_resources_checker.py
dbnd_docker/kubernetes/kubernetes_engine_config.py
dbnd_docker/kubernetes/kubernetes_task_run_ctrl.py
dbnd_docker/kubernetes/compat/__init__.py
dbnd_docker/kubernetes/compat/pod_launcher.py
dbnd_docker/kubernetes/compat/pod_reconciler.py
dbnd_docker/kubernetes/compat/secrets_shim.py
dbnd_docker/kubernetes/compat/volume_shims.py
dbnd_docker/kubernetes/vendorized_airflow/__init__.py
dbnd_docker/kubernetes/vendorized_airflow/dbnd_extended_resources.py
dbnd_docker/kubernetes/vendorized_airflow/request_factory.py
dbnd_docker-1.0.30.1.dist-info/LICENSE
dbnd_docker-1.0.30.1.dist-info/METADATA
dbnd_docker-1.0.30.1.dist-info/WHEEL
dbnd_docker-1.0.30.1.dist-info/entry_points.txt
dbnd_docker-1.0.30.1.dist-info/top_level.txt
dbnd_docker-1.0.30.1.dist-info/RECORD
